{
  "resumo_id": "s10-int1ped-04-000",
  "no_pai_id": "s10-int1ped-00-001",
  "nos_filhos_ids": [
    "s10-int1ped-04-001",
    "s10-int1ped-04-002"
  ],
  "conexoes_laterais_ids": [],
  "metadata": {
    "titulo": "Casos integradores da Pediatria",
    "semestre": 10,
    "disciplina": "Estágio em Pediatria",
    "profundidade_arvore": 1,
    "importancia": 3,
    "dificuldade": 2,
    "tempo_leitura_minutos": 0,
    "status": "esqueleto",
    "data_criacao": "2026-07-01",
    "data_ultima_revisao": "2026-07-01",
    "versao": "0.0",
    "tags": [
      "int1ped",
      "esqueleto"
    ],
    "nivel": "CORE",
    "tipo": "conceito",
    "formato_internato": "visao_geral"
  },
  "resumo_conciso": "Módulo dos casos que cruzam ≥2 sistemas e forçam priorização",
  "narrativa": [],
  "conexoes": {
    "prerequisitos": [],
    "futuras": [],
    "laterais": []
  },
  "flashcards": [],
  "casos_clinicos": [],
  "midia": {
    "imagens": [],
    "videos": [],
    "audios": []
  },
  "horizonte_validade": "estavel",
  "estado_ciclo_vida": "rascunho",
  "nivel_aceitacao": "minimo_viavel",
  "procedencia": {
    "gerado_por": "mapa-blueprint-s10",
    "data_geracao": "2026-07-01",
    "revisado_por": null,
    "data_revisao": null,
    "nivel_confianca": "rascunho"
  },
  "fontes": [],
  "_lentes": [
    "raciocinio_diagnostico",
    "conduta",
    "seguranca_paciente"
  ]
}